MANIFEST.in
setup.py
django_date_range_view/__init__.py
django_date_range_view.egg-info/PKG-INFO
django_date_range_view.egg-info/SOURCES.txt
django_date_range_view.egg-info/dependency_links.txt
django_date_range_view.egg-info/requires.txt
django_date_range_view.egg-info/top_level.txt
django_date_range_view/templates/views/_date_range_nav.html
django_date_range_view/templates/views/date_range_view.html