Metadata-Version: 1.0
Name: django-date-range-view
Version: 0.1.1
Summary: provides a simple date range parsing django view
Home-page: https://bitbucket.org/freakypie/django-date-range-view
Author: John Leith
Author-email: leith.john@gmail.com
License: BSD License
Platform: UNKNOWN
